chatgpt_telegram/__init__.py
chatgpt_telegram/__main__.py
chatgpt_telegram/chatgpt_browser.py
chatgpt_telegram/chatgpt_openai.py
chatgpt_telegram/telegrambot.py
chatgpt_telegram-0.1.4.dist-info/LICENSE
chatgpt_telegram-0.1.4.dist-info/METADATA
chatgpt_telegram-0.1.4.dist-info/WHEEL
chatgpt_telegram-0.1.4.dist-info/entry_points.txt
chatgpt_telegram-0.1.4.dist-info/top_level.txt
chatgpt_telegram-0.1.4.dist-info/RECORD
