Metadata-Version: 2.1
Name: chatgpt-telegram
Version: 0.1.4
Summary: ChatGPT Bot For telegram
Home-page: https://github.com/learnforpractice/chatgpt-telegram
Author: learnforpractice
License: Apache 2.0
License-File: LICENSE
Requires-Dist: pyyaml
Requires-Dist: openai (>=0.27.0)
Requires-Dist: python-telegram-bot
Provides-Extra: browser
Requires-Dist: playwright ; extra == 'browser'
Requires-Dist: cf-clearance ; extra == 'browser'
